ollabridge/__init__.py
ollabridge/mcp_server.py
ollabridge/api/__init__.py
ollabridge/api/auth.py
ollabridge/api/main.py
ollabridge/api/relay.py
ollabridge/api/schemas.py
ollabridge/api/state.py
ollabridge/cli/__init__.py
ollabridge/cli/__main__.py
ollabridge/cli/main.py
ollabridge/cloud/__init__.py
ollabridge/cloud/api_client.py
ollabridge/cloud/device_config.py
ollabridge/connectors/__init__.py
ollabridge/connectors/base.py
ollabridge/connectors/direct_endpoint.py
ollabridge/core/__init__.py
ollabridge/core/enrollment.py
ollabridge/core/keys.py
ollabridge/core/registry.py
ollabridge/core/router.py
ollabridge/core/security.py
ollabridge/core/settings.py
ollabridge/db/__init__.py
ollabridge/db/database.py
ollabridge/db/models.py
ollabridge/mcp/__init__.py
ollabridge/mcp/server.py
ollabridge/mcp/tools.py
ollabridge/node/__init__.py
ollabridge/node/agent.py
ollabridge/node/cli.py
ollabridge/node/runtime.py
ollabridge/providers/__init__.py
ollabridge/providers/ollama_client.py
ollabridge/utils/__init__.py
ollabridge/utils/installer.py
ollabridge/utils/tunnel.py
ollabridge-0.1.1.dist-info/METADATA
ollabridge-0.1.1.dist-info/WHEEL
ollabridge-0.1.1.dist-info/entry_points.txt
ollabridge-0.1.1.dist-info/licenses/LICENSE
ollabridge-0.1.1.dist-info/RECORD
