Metadata-Version: 2.4
Name: ollabridge
Version: 0.1.1
Summary: Turn your PC into a private, OpenAI-compatible LLM provider in ~60 seconds
Project-URL: Homepage, https://github.com/ruslanmv/ollabridge
Project-URL: Documentation, https://github.com/ruslanmv/ollabridge#readme
Project-URL: Repository, https://github.com/ruslanmv/ollabridge
Project-URL: Issues, https://github.com/ruslanmv/ollabridge/issues
Project-URL: Changelog, https://github.com/ruslanmv/ollabridge/releases
Author-email: Ruslan Magana Vsevolodovna <contact@ruslanmv.com>
Maintainer-email: Ruslan Magana Vsevolodovna <contact@ruslanmv.com>
License: 
License-File: LICENSE
Keywords: ai,api,chatgpt,deepseek,embeddings,gateway,langchain,llama,llm,local-first,machine-learning,ollama,openai,self-hosted
Classifier: Development Status :: 4 - Beta
Classifier: Framework :: FastAPI
Classifier: Intended Audience :: Developers
Classifier: Intended Audience :: Science/Research
Classifier: License :: OSI Approved :: Apache Software License
Classifier: Operating System :: OS Independent
Classifier: Programming Language :: Python :: 3
Classifier: Programming Language :: Python :: 3.10
Classifier: Programming Language :: Python :: 3.11
Classifier: Programming Language :: Python :: 3.12
Classifier: Topic :: Internet :: WWW/HTTP :: HTTP Servers
Classifier: Topic :: Scientific/Engineering :: Artificial Intelligence
Classifier: Topic :: Software Development :: Libraries :: Python Modules
Requires-Python: >=3.10
Requires-Dist: anyio
Requires-Dist: fastapi>=0.110
Requires-Dist: httpx>=0.26
Requires-Dist: itsdangerous>=2.1
Requires-Dist: pydantic-settings>=2.2
Requires-Dist: pydantic>=2.6
Requires-Dist: python-dotenv>=1.0
Requires-Dist: pyyaml>=6.0
Requires-Dist: rich>=13.7
Requires-Dist: slowapi
Requires-Dist: sqlalchemy
Requires-Dist: sqlmodel
Requires-Dist: tenacity>=8.2
Requires-Dist: typer>=0.12
Requires-Dist: uvicorn[standard]>=0.27
Requires-Dist: websockets>=12.0
Provides-Extra: dev
Requires-Dist: black>=23.7; extra == 'dev'
Requires-Dist: mypy>=1.4; extra == 'dev'
Requires-Dist: pytest-asyncio>=0.21; extra == 'dev'
Requires-Dist: pytest-cov>=4.1; extra == 'dev'
Requires-Dist: pytest>=7.4; extra == 'dev'
Requires-Dist: ruff>=0.0.280; extra == 'dev'
